outlier_plotting/__init__.py
outlier_plotting/sns.py
outlier_plotting-0.2.1.dist-info/LICENSE
outlier_plotting-0.2.1.dist-info/METADATA
outlier_plotting-0.2.1.dist-info/WHEEL
outlier_plotting-0.2.1.dist-info/top_level.txt
outlier_plotting-0.2.1.dist-info/RECORD
