Metadata-Version: 2.1
Name: outlier-plotting
Version: 0.2.1
Summary: More graceful handling of outliers in plots
Home-page: https://github.com/wendli01/outlier_plotting
Author: Lorenz Wendlinger
Author-email: lorenz.wen@gmx.com
License: UNKNOWN
Platform: UNKNOWN
Classifier: Programming Language :: Python :: 3
Classifier: License :: OSI Approved :: MIT License
Classifier: Operating System :: OS Independent
Requires-Python: >=3.6
Requires-Dist: seaborn (>=0.9)
